[
  {
    "id": "6946ab747610406230d5e1b8",
    "title": "Eduquity Revision Batch",
    "banner": "https://selectionwayserver.hranker.com/courses/banners/1766331686634-1000209920.png",
    "discountPrice": 1
  },
  {
    "id": "694403528b3dd15b95906023",
    "title": "Railway Reasoning Batch",
    "banner": "https://selectionwayserver.hranker.com/courses/banners/1766065229188-Railway_Reasoning_Special_banner_.png",
    "discountPrice": 399
  },
  {
    "id": "6943f165cd0a679bc120abf4",
    "title": "Science Booster Batch",
    "banner": "https://selectionwayserver.hranker.com/courses/banners/1766063157214-science.png",
    "discountPrice": 199
  },
  {
    "id": "6943f10fcd0a679bc1207d93",
    "title": "Railway Foundation Batch -2",
    "banner": "https://selectionwayserver.hranker.com/courses/banners/1766060376051-1763723573427-Railway_Foundation_Batch_App_Banner_11_oct.png",
    "discountPrice": 799
  },
  {
    "id": "69416bb56385517afa46f6fe",
    "title": "UP Lekhpal Special",
    "banner": "https://selectionwayserver.hranker.com/courses/banners/1765896887264-Lekhpal_Categary_poster_.png",
    "discountPrice": 499
  },
  {
    "id": "693ff2801f7d472f7eeac163",
    "title": "NTPC PSYCHO BATCH",
    "banner": "https://selectionwayserver.hranker.com/courses/banners/1765807543021-Railway_psycho_Banner_.png",
    "discountPrice": 999
  },
  {
    "id": "693aa8016385517afa84329d",
    "title": "UP होमगार्ड Batch",
    "banner": "https://selectionwayserver.hranker.com/courses/banners/1765452051272-UP_HomeGuard_Batch_App_Banner_11_oct.png",
    "discountPrice": 199
  },
  {
    "id": "69367eb033d222e80e32c6de",
    "title": "Reasoning Special-3",
    "banner": "https://selectionwayserver.hranker.com/courses/banners/1765351419428-Reasoning_App_Banner_8_Dec__(2).png",
    "discountPrice": 399
  },
  {
    "id": "69367ea733d222e80e32c6d9",
    "title": "English Special-3",
    "banner": "https://selectionwayserver.hranker.com/courses/banners/1765351433141-English_App_Banner_8_Dec__(2).png",
    "discountPrice": 999
  },
  {
    "id": "69367ea133d222e80e32c6ce",
    "title": "Selection Batch-3",
    "banner": "https://selectionwayserver.hranker.com/courses/banners/1765193085808-Selection_Batch_App_Banner_8_Dec_.png",
    "discountPrice": 1399
  },
  {
    "id": "69367e9933d222e80e32c6c9",
    "title": "Maths Special-3",
    "banner": "https://selectionwayserver.hranker.com/courses/banners/1765351840245-Maths_App_Banner_8_Dec__(2).png",
    "discountPrice": 799
  },
  {
    "id": "69367c0233d222e80e32ab9a",
    "title": "GS Special-3",
    "banner": "https://selectionwayserver.hranker.com/courses/banners/1765351890565-GS_App_Banner_8_Dec__(2).png",
    "discountPrice": 399
  },
  {
    "id": "6933f618dd258fd3232fcf33",
    "title": "UPSI 2025 POLITY +मूलविधि",
    "banner": "https://selectionwayserver.hranker.com/courses/banners/1765013045618-poster_mool.jpg",
    "discountPrice": 299
  },
  {
    "id": "6933f35cdd258fd32320c55d",
    "title": "UPSI 2025 दरोगा बैच",
    "banner": "https://selectionwayserver.hranker.com/courses/banners/1765014780000-1000201741.png",
    "discountPrice": 599
  },
  {
    "id": "69329844dd258fd3230f50d7",
    "title": "SSC GD Target Batch",
    "banner": "https://selectionwayserver.hranker.com/courses/banners/1764923541882-SSC_GD_2026_Batch_App_Banner_DEC_.png",
    "discountPrice": 499
  },
  {
    "id": "69204beb39642e9188a548b9",
    "title": "Science Special 2",
    "banner": "https://selectionwayserver.hranker.com/courses/banners/1763724389298-Science_Special_Batch_App_Banner_11_oct.png",
    "discountPrice": 299
  },
  {
    "id": "69204816dd258fd323a45956",
    "title": "Railway Foundation Batch",
    "banner": "https://selectionwayserver.hranker.com/courses/banners/1763723573427-Railway_Foundation_Batch_App_Banner_11_oct.png",
    "discountPrice": 999
  },
  {
    "id": "691d6de4dd258fd32356421a",
    "title": "Railway Group-D Science VOD Batch",
    "banner": "https://selectionwayserver.hranker.com/courses/banners/1763734711985-IMG_20251121_183028_370_(2).jpg",
    "discountPrice": 99
  },
  {
    "id": "69150be0932c0deb70330767",
    "title": "Maths Special VOD Batch",
    "banner": "https://selectionwayserver.hranker.com/courses/banners/1766734589950-vod_banner.jpeg",
    "discountPrice": 599
  },
  {
    "id": "690b0fa65085387730114664",
    "title": "Maths Special-2",
    "banner": "https://selectionwayserver.hranker.com/courses/banners/1765199172618-WhatsApp_Image_2025-12-08_at_6.33.10_PM_(2).jpeg",
    "discountPrice": 999
  },
  {
    "id": "690b0ee719fedfd663790697",
    "title": "English Special-2",
    "banner": "https://selectionwayserver.hranker.com/courses/banners/1765199189747-WhatsApp_Image_2025-12-08_at_6.33.10_PM_(1).jpeg",
    "discountPrice": 999
  },
  {
    "id": "690b0e556aeca24e9398c340",
    "title": "Reasoning Special-2",
    "banner": "https://selectionwayserver.hranker.com/courses/banners/1765199217026-WhatsApp_Image_2025-12-08_at_6.33.11_PM.jpeg",
    "discountPrice": 399
  },
  {
    "id": "690b0cdc6aeca24e9397ab6f",
    "title": "Selection Batch-2",
    "banner": "https://selectionwayserver.hranker.com/courses/banners/1765199237740-WhatsApp_Image_2025-12-08_at_6.33.09_PM.jpeg",
    "discountPrice": 1999
  },
  {
    "id": "690afc8bf48d1caffd0c0319",
    "title": "GS Special-2",
    "banner": "https://selectionwayserver.hranker.com/courses/banners/1765199250481-WhatsApp_Image_2025-12-08_at_6.33.08_PM.jpeg",
    "discountPrice": 399
  },
  {
    "id": "68ef76338b84905b84eebde7",
    "title": "Vocab Mastery VOD Batch",
    "banner": "https://selectionwayserver.hranker.com/courses/banners/1766897927376-aman_sir_main_level_red.jpg",
    "discountPrice": 499
  },
  {
    "id": "68e7b6e6aaf4383d1192dfb6",
    "title": "SSC MAINS ENGLISH BATCH",
    "banner": "https://selectionwayserver.hranker.com/courses/banners/1760450276577-1760426657317-IMG_4799.png",
    "discountPrice": 499
  },
  {
    "id": "68e7b92dd191c00e5c8d713e",
    "title": "SSC MAINS MATHS BATCH",
    "banner": "https://selectionwayserver.hranker.com/courses/banners/1760450156815-1760426810209-IMG_4798.png",
    "discountPrice": 499
  },
  {
    "id": "68e27174dfde12332485c494",
    "title": "SSC Mains Batch",
    "banner": "https://selectionwayserver.hranker.com/courses/banners/1760450361199-1760426421325-IMG_4796.png",
    "discountPrice": 999
  },
  {
    "id": "68dbd603f975d67976534e12",
    "title": "Selection Batch-1",
    "banner": "https://selectionwayserver.hranker.com/courses/banners/1760708317029-IMG_4791.png",
    "discountPrice": 1599
  },
  {
    "id": "68dbd69163a1698bf4194575",
    "title": "GS Special-1",
    "banner": "https://selectionwayserver.hranker.com/courses/banners/1760450520522-1760427023576-IMG_4803.png",
    "discountPrice": 999
  },
  {
    "id": "68dbd66763a1698bf4194574",
    "title": "Reasoning Special-1",
    "banner": "https://selectionwayserver.hranker.com/courses/banners/1760450562395-1760427060701-IMG_4804.png",
    "discountPrice": 999
  },
  {
    "id": "68dbd32801d050d5b62e45cc",
    "title": "Science Special foundation Batch",
    "banner": "https://selectionwayserver.hranker.com/courses/banners/1762335998045-harish_sir_red_Science.png",
    "discountPrice": 399
  },
  {
    "id": "68dbdf3a63a1698bf4194576",
    "title": "RRB Group-D Target batch",
    "banner": "https://selectionwayserver.hranker.com/courses/banners/1762333624056-harish_sir_red.png",
    "discountPrice": 99
  },
  {
    "id": "68dbd51563a1698bf4194573",
    "title": "English Special-1",
    "banner": "https://selectionwayserver.hranker.com/courses/banners/1760450597110-1760426744178-IMG_4801.png",
    "discountPrice": 799
  },
  {
    "id": "68d7a797209cc08d6e31f672",
    "title": "maths recorded gagan pratap sir",
    "banner": "https://hranker-node.s3.ap-south-1.amazonaws.com/courses/banners/1758963607762-desktop-wallpaper-black-board-ppt-backgrounds-powerpoint-backgrounds-coloring-background-ppt-simple.jpg",
    "discountPrice": 1000
  },
  {
    "id": "68d6550a99a6043c5d2dbca1",
    "title": "SSC 2024 Exams Best Questions Solution",
    "banner": "https://selectionwayserver.hranker.com/courses/banners/1760470294013-1758876938156-ssc2024image.jpg",
    "discountPrice": 1000
  },
  {
    "id": "68ce5fe8bb3c8f24bb3d4f77",
    "title": "Maths Special-1",
    "banner": "https://selectionwayserver.hranker.com/courses/banners/1760450679425-1760426839758-IMG_4802.png",
    "discountPrice": 999
  },
  {
    "id": "68be7de9a721af475c9b04b4",
    "title": "सम्पूर्ण BATCH MATHS SPECIAL",
    "banner": "https://selectionwayserver.hranker.com/courses/banners/1760471352273-1758391605769-1757325458544-hqdefault_(4).jpg",
    "discountPrice": 1000
  },
  {
    "id": "68bc5c26a721af475c9ac2a5",
    "title": "RAILWAY FREE BATCH",
    "banner": "https://selectionwayserver.hranker.com/courses/banners/1760471391652-1000066549.jpeg",
    "discountPrice": 1000
  },
  {
    "id": "68bc5bc8a721af475c9ac21f",
    "title": "RAILWAY ADVANCE MATHS",
    "banner": "https://selectionwayserver.hranker.com/courses/banners/1760471423381-1757313832053-hqdefault_(1).jpg",
    "discountPrice": 1000
  },
  {
    "id": "68bc5ba8a721af475c9ac19b",
    "title": "SSC MATHS PYQ SERIES",
    "banner": "https://selectionwayserver.hranker.com/courses/banners/1760471460820-1000066551_(1).jpeg",
    "discountPrice": 1000
  },
  {
    "id": "68bc5b80a721af475c9ac115",
    "title": "COMPLETE ADVANCE MATHS",
    "banner": "https://selectionwayserver.hranker.com/courses/banners/1760471651145-1757313913587-hqdefault_(3).jpg",
    "discountPrice": 1000
  },
  {
    "id": "684050f55db342bb13da8211",
    "title": "SSC Recorded Batch",
    "banner": "https://selectionwayserver.hranker.com/courses/banners/1760471722724-cors.png",
    "discountPrice": 999
  },
  {
    "id": "683def9c2f4523ef6c8b18cb",
    "title": "Defence all in one",
    "banner": "https://selectionwayserver.hranker.com/courses/banners/1760471757956-image.png",
    "discountPrice": 999
  },
  {
    "id": "683def9c2f4523ef6c8b18bd",
    "title": "Railways- all in one",
    "banner": "https://selectionwayserver.hranker.com/courses/banners/1760471946067-imaged.png",
    "discountPrice": 999
  },
  {
    "id": "68a6be03a741c9fd7187fca3",
    "title": "Railway all in one - 2",
    "banner": "https://selectionwayserver.hranker.com/courses/banners/1760472022990-imaged.png",
    "discountPrice": 999
  },
  {
    "id": "683def9c2f4523ef6c8b18b7",
    "title": "SSC all in one",
    "banner": "https://selectionwayserver.hranker.com/courses/banners/1760471989254-cors.png",
    "discountPrice": 1000
  },
  {
    "id": "683def9c2f4523ef6c8b18c5",
    "title": "Defence- all in one",
    "banner": "https://selectionwayserver.hranker.com/courses/banners/1760471969470-image.png",
    "discountPrice": 999
  },
  {
    "id": "683def9c2f4523ef6c8b18ae",
    "title": "Railway all in one",
    "banner": "https://selectionwayserver.hranker.com/courses/banners/1760472038888-imaged.png",
    "discountPrice": 999
  }
]
